error_repository_server/__init__.py
error_repository_server/__main__.py
error_repository_server/server.py
error_repository_server-0.1.0.dist-info/METADATA
error_repository_server-0.1.0.dist-info/WHEEL
error_repository_server-0.1.0.dist-info/entry_points.txt
error_repository_server-0.1.0.dist-info/licenses/LICENSE
error_repository_server-0.1.0.dist-info/RECORD
