Metadata-Version: 2.4
Name: error-repository-server
Version: 0.1.0
Summary: MCP server for error repository that answers questions about error codes and solutions
Project-URL: Homepage, https://github.com/yourusername/error-repository-server
Project-URL: Repository, https://github.com/yourusername/error-repository-server
Project-URL: Bug Tracker, https://github.com/yourusername/error-repository-server/issues
Project-URL: Documentation, https://github.com/yourusername/error-repository-server/blob/main/README.md
Author-email: Your Name <your.email@example.com>
License: MIT
License-File: LICENSE
Keywords: debugging,error-codes,error-repository,mcp,model-context-protocol
Classifier: Development Status :: 4 - Beta
Classifier: Intended Audience :: Developers
Classifier: License :: OSI Approved :: MIT License
Classifier: Programming Language :: Python :: 3
Classifier: Programming Language :: Python :: 3.8
Classifier: Programming Language :: Python :: 3.9
Classifier: Programming Language :: Python :: 3.10
Classifier: Programming Language :: Python :: 3.11
Classifier: Programming Language :: Python :: 3.12
Classifier: Topic :: Software Development :: Libraries :: Python Modules
Classifier: Topic :: System :: Systems Administration
Requires-Python: >=3.8
Requires-Dist: mcp>=1.0.0
Requires-Dist: openpyxl>=3.1.0
Requires-Dist: pandas>=2.0.0
Requires-Dist: pydantic>=2.0.0
